Metadata-Version: 1.1
Name: unimi-unsubscribe
Version: 0.0.1
Summary: Simple package to stop receiving annoying emails from Unimi.
Home-page: https://github.com/LucaCappelletti94/unimi_unsubscribe
Author: Luca Cappelletti
Author-email: cappelletti.luca94@gmail.com
License: MIT
Platform: UNKNOWN
Classifier: Development Status :: 4 - Beta
Classifier: License :: OSI Approved :: MIT License
Classifier: Programming Language :: Python :: 3
